pywe_component_authorizer_token/__init__.py
pywe_component_authorizer_token/basetoken.py
pywe_component_authorizer_token/token.py
pywe_component_authorizer_token-1.1.1.dist-info/METADATA
pywe_component_authorizer_token-1.1.1.dist-info/RECORD
pywe_component_authorizer_token-1.1.1.dist-info/WHEEL
pywe_component_authorizer_token-1.1.1.dist-info/top_level.txt
