Metadata-Version: 2.1
Name: pywe-component-authorizer-token
Version: 1.1.1
Summary: Wechat Component Authorizer Token Module for Python.
Home-page: https://github.com/sdkwe/pywe-component-authorizer-token
Author: Hackathon
Author-email: kimi.huang@brightcells.com
License: UNKNOWN
Keywords: Wechat Weixin Component Authorizer Token
Platform: UNKNOWN
Classifier: License :: OSI Approved :: BSD License
Classifier: Programming Language :: Python
Classifier: Programming Language :: Python :: 2
Classifier: Programming Language :: Python :: 2.6
Classifier: Programming Language :: Python :: 2.7
Classifier: Programming Language :: Python :: 3
Classifier: Programming Language :: Python :: 3.2
Classifier: Programming Language :: Python :: 3.3
Classifier: Programming Language :: Python :: 3.4
Classifier: Programming Language :: Python :: 3.5
Classifier: Programming Language :: Python :: 3.6
Classifier: Topic :: Software Development :: Libraries :: Python Modules
Requires-Dist: pywe-base
Requires-Dist: pywe-component-token
Requires-Dist: pywe-exception
Requires-Dist: pywe-storage
